{
  "contest_like": true,
  "ds_version": "0.0",
  "left_white_overexposed": true,
  "objects": [
    {
      "data": [
        [
          2127.0,
          1351.0
        ],
        [
          2324.0,
          1210.0
        ],
        [
          2329.0,
          1437.0
        ]
      ],
      "tags": [
        "left"
      ],
      "type": "region"
    },
    {
      "data": [
        [
          2324.0,
          1210.0
        ],
        [
          2530.0,
          1322.0
        ],
        [
          2329.0,
          1435.0
        ]
      ],
      "tags": [
        "right"
      ],
      "type": "region"
    },
    {
      "data": [
        [
          2125.0,
          1578.0
        ],
        [
          2127.0,
          1349.0
        ],
        [
          2325.0,
          1435.0
        ]
      ],
      "tags": [
        "left_b"
      ],
      "type": "region"
    },
    {
      "data": [
        [
          2547.0,
          1558.0
        ],
        [
          2531.0,
          1321.0
        ],
        [
          2328.0,
          1434.0
        ]
      ],
      "tags": [
        "right_b"
      ],
      "type": "region"
    }
  ],
  "original_gt": [
    0.19842556,
    0.46804816,
    0.33352628
  ],
  "original_left_gt": [
    0.19842556,
    0.46804816,
    0.33352628
  ],
  "original_right_gt": [
    0.20004181,
    0.4673913,
    0.33256689
  ],
  "properties": {
    "daytime": "day",
    "estimation": "partial",
    "gdpr_objects": [
      "none"
    ],
    "has_cube_plus": true,
    "has_known_objects": true,
    "illumination": "natural",
    "is_sharp": true,
    "light_objects": [
      "none"
    ],
    "place": "outdoor",
    "richness": "rich",
    "shadows": "no"
  },
  "right_white_overexposed": true,
  "size": [
    2592,
    1728
  ]
}