{
  "ds_version": "1.0",
  "left_white_overexposed": false,
  "objects": [
    {
      "data": [
        [
          1999.0,
          1265.0
        ],
        [
          2198.0,
          1145.0
        ],
        [
          2193.0,
          1366.0
        ]
      ],
      "tags": [
        "left"
      ],
      "type": "region"
    },
    {
      "data": [
        [
          1986.0,
          1491.0
        ],
        [
          2192.0,
          1366.0
        ],
        [
          1998.0,
          1266.0
        ]
      ],
      "tags": [
        "left_b"
      ],
      "type": "region"
    },
    {
      "data": [
        [
          2411.0,
          1262.0
        ],
        [
          2198.0,
          1145.0
        ],
        [
          2192.0,
          1365.0
        ]
      ],
      "tags": [
        "right"
      ],
      "type": "region"
    },
    {
      "data": [
        [
          2419.0,
          1497.0
        ],
        [
          2410.0,
          1260.0
        ],
        [
          2194.0,
          1364.0
        ]
      ],
      "tags": [
        "right_b"
      ],
      "type": "region"
    }
  ],
  "original_gt": [
    0.19308511,
    0.46542553,
    0.34148936
  ],
  "properties": {
    "daytime": "unknown",
    "estimation": "full",
    "gdpr_objects": [
      "none"
    ],
    "has_cube_plus": true,
    "has_known_objects": false,
    "illumination": "unknown",
    "is_sharp": true,
    "light_objects": [
      "none"
    ],
    "place": "outdoor",
    "richness": "simple",
    "shadows": "no"
  },
  "right_white_overexposed": false,
  "size": [
    2592,
    1728
  ]
}