{
  "ds_version": "2.0",
  "left_white_overexposed": false,
  "objects": [
    {
      "data": [
        [
          2387.0,
          1617.0
        ],
        [
          2187.0,
          1457.0
        ],
        [
          2358.0,
          1435.0
        ]
      ],
      "tags": [
        "right_b"
      ],
      "type": "region"
    },
    {
      "data": [
        [
          2358.0,
          1435.0
        ],
        [
          2187.0,
          1457.0
        ],
        [
          2176.0,
          1288.0
        ]
      ],
      "tags": [
        "right"
      ],
      "type": "region"
    },
    {
      "data": [
        [
          1978.0,
          1594.0
        ],
        [
          2187.0,
          1456.0
        ],
        [
          1984.0,
          1413.0
        ]
      ],
      "tags": [
        "left_b"
      ],
      "type": "region"
    },
    {
      "data": [
        [
          1983.0,
          1412.0
        ],
        [
          2187.0,
          1456.0
        ],
        [
          2176.0,
          1290.0
        ]
      ],
      "tags": [
        "left"
      ],
      "type": "region"
    }
  ],
  "properties": {
    "daytime": "day",
    "estimation": "full",
    "gdpr_objects": [
      "none"
    ],
    "has_cube_plus": true,
    "has_known_objects": true,
    "illumination": "natural",
    "is_sharp": true,
    "light_objects": [
      "sky"
    ],
    "place": "outdoor",
    "richness": "rich",
    "shadows": "yes"
  },
  "right_white_overexposed": false,
  "size": [
    2592,
    1728
  ]
}