{
  "ds_version": "2.0",
  "left_white_overexposed": false,
  "objects": [
    {
      "data": [
        [
          2099.0,
          1352.0
        ],
        [
          2299.0,
          1381.0
        ],
        [
          2303.0,
          1212.0
        ]
      ],
      "tags": [
        "left"
      ],
      "type": "region"
    },
    {
      "data": [
        [
          2507.0,
          1548.0
        ],
        [
          2503.0,
          1371.0
        ],
        [
          2301.0,
          1381.0
        ]
      ],
      "tags": [
        "right_b"
      ],
      "type": "region"
    },
    {
      "data": [
        [
          2502.0,
          1371.0
        ],
        [
          2300.0,
          1382.0
        ],
        [
          2303.0,
          1214.0
        ]
      ],
      "tags": [
        "right"
      ],
      "type": "region"
    },
    {
      "data": [
        [
          2085.0,
          1532.0
        ],
        [
          2100.0,
          1351.0
        ],
        [
          2298.0,
          1382.0
        ]
      ],
      "tags": [
        "left_b"
      ],
      "type": "region"
    }
  ],
  "properties": {
    "daytime": "unknown",
    "estimation": "full",
    "gdpr_objects": [
      "none"
    ],
    "has_cube_plus": true,
    "has_known_objects": false,
    "illumination": "unknown",
    "is_sharp": false,
    "light_objects": [
      "none"
    ],
    "place": "outdoor",
    "richness": "rich",
    "shadows": "no"
  },
  "right_white_overexposed": true,
  "size": [
    2592,
    1728
  ]
}